CHANGES.txt
LICENSE.txt
README.txt
bootstrap.py
setup.py
src/p01/__init__.py
src/p01.accelerator.egg-info/PKG-INFO
src/p01.accelerator.egg-info/SOURCES.txt
src/p01.accelerator.egg-info/dependency_links.txt
src/p01.accelerator.egg-info/entry_points.txt
src/p01.accelerator.egg-info/namespace_packages.txt
src/p01.accelerator.egg-info/not-zip-safe
src/p01.accelerator.egg-info/requires.txt
src/p01.accelerator.egg-info/top_level.txt
src/p01/accelerator/README.txt
src/p01/accelerator/__init__.py
src/p01/accelerator/configure.zcml
src/p01/accelerator/interfaces.py
src/p01/accelerator/publication.py
src/p01/accelerator/publisher.py
src/p01/accelerator/tests.py
src/p01/accelerator/wsgi.py
src/p01/accelerator/generations/__init__.py
src/p01/accelerator/generations/configure.zcml