Metadata-Version: 1.0
Name: p01.accelerator
Version: 0.5.0
Summary: Browser request and response offering zero-copy file upload post processing for Zope3
Home-page: http://cheeseshop.python.org/pypi/p01.accelerator
Author: Roger Ineichen, Projekt01 GmbH
Author-email: dev@projekt01.ch
License: ZPL 2.1
Keywords: Zope3 z3c p01 zero-copy browser request response file upload
Platform: UNKNOWN
Classifier: Development Status :: 4 - Beta
Classifier: Environment :: Web Environment
Classifier: Intended Audience :: Developers
Classifier: License :: OSI Approved :: Zope Public License
Classifier: Programming Language :: Python
Classifier: Natural Language :: English
Classifier: Operating System :: OS Independent
Classifier: Topic :: Internet :: WWW/HTTP
Classifier: Framework :: Zope3
